clustertools/__init__.py
clustertools/analysis/Untitled.ipynb
clustertools/analysis/__init__.py
clustertools/analysis/cluster.py
clustertools/analysis/functions.py
clustertools/analysis/initialize.py
clustertools/analysis/load.py
clustertools/analysis/operations.py
clustertools/analysis/orbit.py
clustertools/analysis/orbits.py
clustertools/analysis/profiles.py
clustertools/analysis/tails.py
clustertools/cluster/__init__.py
clustertools/cluster/cluster.py
clustertools/cluster/clusterwplanets.py
clustertools/cluster/initialize.py
clustertools/cluster/load.py
clustertools/cluster/operations.py
clustertools/custom/__init__.py
clustertools/custom/custom_functions.py
clustertools/custom/custom_loaders.py
clustertools/custom/custom_outputs.py
clustertools/custom/test_custom_functions.py
clustertools/io/__init__.py
clustertools/io/amuse.py
clustertools/io/astropy_table.py
clustertools/io/galpydf.py
clustertools/io/gyrfalcon.py
clustertools/io/initialize.py
clustertools/io/limepydf.py
clustertools/io/load.py
clustertools/io/nbody6.py
clustertools/io/nbody6pp.py
clustertools/io/orbit.py
clustertools/io/snapshot.py
clustertools/io/data/deBoer2019.dat
clustertools/io/data/harris2010.dat
clustertools/planet/__init__.py
clustertools/planet/clusterwplanets.py
clustertools/simulate/tailspray.py
clustertools/tidaltail/__init__.py
clustertools/tidaltail/tails.py
clustertools/util/__init__.py
clustertools/util/constants.py
clustertools/util/coordinates.py
clustertools/util/output.py
clustertools/util/plots.py
clustertools/util/recipes.py
clustertools/util/units.py
clustertools-1.0.3.dist-info/LICENSE
clustertools-1.0.3.dist-info/METADATA
clustertools-1.0.3.dist-info/WHEEL
clustertools-1.0.3.dist-info/top_level.txt
clustertools-1.0.3.dist-info/RECORD
