Metadata-Version: 2.1
Name: clustertools
Version: 1.0.3
Summary: A python packaged for analysing star clusters
Author: Jeremy J. Webb
Author-email: webb@astro.utoronto.ca
License: MIT
License-File: LICENSE
Requires-Dist: galpy
Requires-Dist: seaborn
Requires-Dist: numba
